lucit_ubdcc_shared_modules/LicensingManager.cpython-312-i386-linux-gnu.so
lucit_ubdcc_shared_modules/RestEndpointsBase.cpython-312-i386-linux-gnu.so
lucit_ubdcc_shared_modules/Database.cpython-312-i386-linux-gnu.so
lucit_ubdcc_shared_modules/__init__.cpython-312-i386-linux-gnu.so
lucit_ubdcc_shared_modules/App.cpython-312-i386-linux-gnu.so
lucit_ubdcc_shared_modules/RestServer.cpython-312-i386-linux-gnu.so
lucit_ubdcc_shared_modules/LicensingExceptions.cpython-312-i386-linux-gnu.so
lucit_ubdcc_shared_modules/ServiceBase.cpython-312-i386-linux-gnu.so
lucit_ubdcc_shared_modules-0.1.4.dist-info/top_level.txt
lucit_ubdcc_shared_modules-0.1.4.dist-info/RECORD
lucit_ubdcc_shared_modules-0.1.4.dist-info/METADATA
lucit_ubdcc_shared_modules-0.1.4.dist-info/WHEEL
