Metadata-Version: 2.1
Name: lucit-ubdcc-shared-modules
Version: 0.1.4
Summary: LUCIT UBDCC Shared Modules
Home-page: https://github.com/LUCIT-Systems-and-Development/unicorn-depthcache-cluster-for-binance
Author: LUCIT Systems and Development
Author-email: info@lucit.tech
License: LSOSL - LUCIT Synergetic Open Source License
Project-URL: Howto, https://www.lucit.tech/unicorn-depthcache-cluster-for-binance.html#howto
Project-URL: Documentation, https://www.lucit.tech/unicorn-depthcache-cluster-for-binance.html
Project-URL: Wiki, https://github.com/LUCIT-Systems-and-Development/unicorn-depthcache-cluster-for-binance/wiki
Project-URL: Author, https://www.lucit.tech
Project-URL: Changes, https://github.com/LUCIT-Systems-and-Development/unicorn-depthcache-cluster-for-binance/blob/master/packages/lucit-ubdcc-mgmt/CHANGELOG.md
Project-URL: License, https://github.com/LUCIT-Systems-and-Development/unicorn-depthcache-cluster-for-binance/blob/master/LICENSE
Project-URL: Issue Tracker, https://github.com/LUCIT-Systems-and-Development/unicorn-depthcache-cluster-for-binance/issues
Project-URL: Chat, https://gitter.im/unicorn-trading-suite/unicorn-depthcache-cluster-for-binance
Project-URL: Telegram, https://t.me/unicorndevs
Project-URL: Get Support, https://www.lucit.tech/get-support.html
Project-URL: LUCIT Online Shop, https://shop.lucit.services/software/unicorn-depthcache-cluster-for-binance
Classifier: Development Status :: 4 - Beta
Classifier: Programming Language :: Python :: 3.12
Classifier: Programming Language :: Cython
Classifier: License :: Other/Proprietary License
Classifier: Intended Audience :: Developers
Classifier: Intended Audience :: Financial and Insurance Industry
Classifier: Intended Audience :: Information Technology
Classifier: Intended Audience :: Science/Research
Classifier: Operating System :: OS Independent
Classifier: Topic :: Office/Business :: Financial :: Investment
Classifier: Topic :: Software Development :: Libraries :: Python Modules
Classifier: Framework :: AsyncIO
Requires-Python: >=3.12.0
Requires-Dist: aiohttp
Requires-Dist: Cython
Requires-Dist: fastapi
Requires-Dist: kubernetes
Requires-Dist: lucit-licensing-python>=1.8.2
Requires-Dist: uvicorn
